biomojify/__init__.py
biomojify/biomojify.py
biomojify/biomojify_map.py
biomojify/biomojify_test.py
biomojify-0.3.1.0.dist-info/LICENSE
biomojify-0.3.1.0.dist-info/METADATA
biomojify-0.3.1.0.dist-info/WHEEL
biomojify-0.3.1.0.dist-info/entry_points.txt
biomojify-0.3.1.0.dist-info/top_level.txt
biomojify-0.3.1.0.dist-info/RECORD
